resume_as_code/__init__.py
resume_as_code/resume_generation.py
resume_as_code/util.py
resume_as_code/validation.py
resume_as_code-0.0.12.dist-info/LICENSE
resume_as_code-0.0.12.dist-info/WHEEL
resume_as_code-0.0.12.dist-info/METADATA
resume_as_code-0.0.12.dist-info/RECORD
