Metadata-Version: 2.1
Name: resume-as-code
Version: 0.0.12
Summary: A tool for automatic resume generation based on Jinja-Word-templates and YAML-files
Author: Tim Van Erum
Author-email: tim.vanerum@dataroots.io
Requires-Python: >=3.6.0,<4.0.0
Classifier: Programming Language :: Python :: 3
Classifier: Programming Language :: Python :: 3.10
Classifier: Programming Language :: Python :: 3.6
Classifier: Programming Language :: Python :: 3.7
Classifier: Programming Language :: Python :: 3.8
Classifier: Programming Language :: Python :: 3.9
Requires-Dist: Cerberus (>=1.3,<2.0)
Requires-Dist: Jinja2 (>=3,<4)
Requires-Dist: PyYAML (>=6,<7)
Requires-Dist: docxtpl (>=0.15.2,<0.16.0)
Requires-Dist: python-docx (>=0.8.11,<0.9.0)
Requires-Dist: python-dotenv (>=0.19.2,<0.20.0)
Requires-Dist: python-magic (>=0.4.24,<0.5.0)
Requires-Dist: requests (>=2.27.1,<3.0.0)
Requires-Dist: validators (>=0.18.2,<0.19.0)
